{
  "blogs": [
    {
      "title": "My First Blog",
      "body": "lorem0...............................",
      "author": "faiaz",
      "id": 1
    },
    {
      "title": "eksho din e react.js shikhun",
      "body": "lorem0...............................",
      "author": "mursalin",
      "id": 2
    },
    {
      "title": "crash course of jibon, hoye jan smart",
      "body": "lorem0...............................",
      "author": "faiaz",
      "id": 3
    },
    {
      "title": "fdsaA",
      "body": "FDSFASD",
      "author": "mario",
      "id": 6
    },
    {
      "title": "testing 5",
      "body": "fadfadfas",
      "author": "mario",
      "id": 8
    }
  ]
}